googlesheetsdb/__init__.py
googlesheetsdb/client.py
googlesheetsdb-1.0.2.dist-info/METADATA
googlesheetsdb-1.0.2.dist-info/WHEEL
googlesheetsdb-1.0.2.dist-info/top_level.txt
googlesheetsdb-1.0.2.dist-info/RECORD
